tse_option/__init__.py
tse_option/example.py
tse_option-0.1.2.3.dist-info/LICENSE
tse_option-0.1.2.3.dist-info/METADATA
tse_option-0.1.2.3.dist-info/WHEEL
tse_option-0.1.2.3.dist-info/top_level.txt
tse_option-0.1.2.3.dist-info/RECORD
