Metadata-Version: 2.1
Name: tse_option
Version: 0.1.2.3
Summary: Option pricing in Tehran Stock Exchange (TSE) and Iran Farabourse (IFB)
Author-email: Seyed Mohammad Sokout <sm.sokut@gmail.com>
Project-URL: Homepage, https://github.com/sm-sokout/tse-option
Keywords: Tehran Stock Exchange,TSE,Iran Farabourse,IFB,Option pricing,BSM
Classifier: Programming Language :: Python :: 3
Classifier: License :: OSI Approved :: MIT License
Classifier: Operating System :: OS Independent
Requires-Python: >=3.7
License-File: LICENSE
Requires-Dist: numpy
Requires-Dist: pandas
Requires-Dist: scipy
Requires-Dist: requests
Requires-Dist: jalali-pandas
Provides-Extra: dev
Requires-Dist: numpy ; extra == 'dev'
Requires-Dist: pandas ; extra == 'dev'
Requires-Dist: scipy ; extra == 'dev'
Requires-Dist: requests ; extra == 'dev'
Requires-Dist: jalali-pandas ; extra == 'dev'
